{
  "ok": true,
  "schedulerEngine": "cloudflare-worker-daily-v3-catchup",
  "deliveryMode": "onesignal-timezone",
  "schedulerStatus": "success",
  "updatedAt": "2026-07-04T11:20:33.964Z",
  "usersChecked": 17,
  "duaCandidates": 0,
  "recCandidates": 17,
  "sent": 17,
  "skipped": 0,
  "duplicates": 17,
  "errors": 0,
  "dailyContentDate": "2026-07-04",
  "currentRecommendation": {
    "id": "usul-des-manhaj-ahl-al-ahwa-nicht-das-herz-oeffnen-257",
    "title": "Uṣūl des Manhaj: Ahl al-Ahwāʾ nicht das Herz öffnen",
    "category": "Uṣūl des Manhaj",
    "scholar": "Muḥammad ibn Sīrīn"
  },
  "currentDua": {
    "id": "sunnah-008",
    "title": "Duʿāʾ beim Betreten der Moschee",
    "category": "Moschee"
  },
  "configAutomatic": true,
  "responses": [
    {
      "kind": "recommendation",
      "batch": true,
      "count": 17,
      "contentId": "usul-des-manhaj-ahl-al-ahwa-nicht-das-herz-oeffnen-257",
      "recipients": "7e2a4c5b-777e-4b73-97a4-fcc9134e4f8b",
      "ok": true,
      "invalid": 0
    }
  ]
}
