{
  "ok": false,
  "schedulerEngine": "cloudflare-worker-daily-v3-catchup",
  "deliveryMode": "onesignal-timezone",
  "schedulerStatus": "error",
  "updatedAt": "2026-07-01T11:15:10.878Z",
  "usersChecked": 17,
  "duaCandidates": 0,
  "recCandidates": 17,
  "sent": 0,
  "skipped": 0,
  "duplicates": 17,
  "errors": 17,
  "dailyContentDate": "2026-07-01",
  "currentRecommendation": {
    "id": "sufyan-ath-thawri-gewissheit-allah-nicht-anklagen-431",
    "title": "Gewissheit bedeutet, Allāh nicht anzuklagen",
    "category": "Tazkiyah",
    "scholar": "Sufyān ath-Thawrī"
  },
  "currentDua": {
    "id": "sunnah-005",
    "title": "Ruqyah bei Krankheit",
    "category": "Krankheit"
  },
  "configAutomatic": true,
  "responses": [
    {
      "kind": "recommendation",
      "batch": true,
      "count": 17,
      "contentId": "sufyan-ath-thawri-gewissheit-allah-nicht-anklagen-431",
      "recipients": "8a88b956-1bea-438b-a10a-2376c7b08587",
      "ok": false,
      "invalid": 6
    }
  ]
}
